.editorconfig
.gitignore
.travis.yml
AUTHORS.rst
CONTRIBUTING.rst
HISTORY.rst
LICENSE
MANIFEST.in
Makefile
README.rst
pytest.ini
requirements_dev.txt
setup.cfg
setup.py
tox.ini
.github/ISSUE_TEMPLATE.md
docs/Makefile
docs/authors.rst
docs/conf.py
docs/contributing.rst
docs/history.rst
docs/index.rst
docs/installation.rst
docs/make.bat
docs/readme.rst
docs/usage.rst
examples/config.yaml
examples/config_fetch.yaml
examples/config_hartools.yaml
examples/config_vfld.yaml
examples/env.sh
examples/pyd_ex.py
examples/test_lib.py
hartools/__init__.py
hartools/cli.py
hartools/hartools.py
hartools.egg-info/PKG-INFO
hartools.egg-info/SOURCES.txt
hartools.egg-info/dependency_links.txt
hartools.egg-info/entry_points.txt
hartools.egg-info/not-zip-safe
hartools.egg-info/top_level.txt
hartools/harecfs/ecfs.py
hartools/hario/vfld.py
hartools/hario/vobs.py
hartools/harmon/__init__.py
hartools/harmon/config.py
hartools/harmon/count_days_ecfs.py
hartools/harmon/log_timestamps.py
hartools/harmon/progress_utils.py
hartools/harmon/streams.yaml
tests/__init__.py
tests/run_tests.sh
tests/test_hartools.py
tests/test_vobs.py
tests/vobsTests.py
tests/vobs_sample.tgz