Metadata-Version: 2.1
Name: hartools
Version: 0.1.4
Summary: Tools for processing data and monitoring output from the Harmonie arome model
Home-page: https://github.com/carlos9917/hartools
Author: Carlos Peralta
Author-email: carlos9917@gmail.com
License: MIT license
Keywords: hartools
Platform: UNKNOWN
Classifier: Development Status :: 2 - Pre-Alpha
Classifier: Intended Audience :: Developers
Classifier: License :: OSI Approved :: MIT License
Classifier: Natural Language :: English
Classifier: Programming Language :: Python :: 3
Classifier: Programming Language :: Python :: 3.6
Classifier: Programming Language :: Python :: 3.7
Classifier: Programming Language :: Python :: 3.8
Requires-Python: >=3.6
License-File: LICENSE
License-File: AUTHORS.rst
